Workbook

Sheet Dashboard
A1: DASHBOARD DE FLUXO DE CAIXA & LIQUIDEZ
N2: Mês | O2: Entradas | P2: Saídas | Q2: Saldo | R2: Liquidez
A3: Visão gerencial | Realizado Jan–Ago/2026 + Projeção Set–Dez/2026 | N3: Jan | O3: =Resumo_Mensal!D4 -> 82000 | P3: =Resumo_Mensal!E4 -> 68000 | Q3: =Resumo_Mensal!G4 -> 64000 | R3: =Resumo_Mensal!J4 -> 3.0294118
N4: Fev | O4: =Resumo_Mensal!D5 -> 79000 | P4: =Resumo_Mensal!E5 -> 72000 | Q4: =Resumo_Mensal!G5 -> 71000 | R4: =Resumo_Mensal!J5 -> 3.0447531
A5: Saldo Inicial (R$) | C5: Entradas 2026 (R$) | E5: Saídas 2026 (R$) | G5: Saldo Final (R$) | I5: Liquidez Dez/26 | K5: Cobertura de Caixa | N5: Mar | O5: =Resumo_Mensal!D6 -> 91000 | P5: =Resumo_Mensal!E6 -> 74500 | Q5: =Resumo_Mensal!G6 -> 87500 | R5: =Resumo_Mensal!J6 -> 3.5600298
A6: =ROUND(Premissas!B4,0) -> 50000 | C6: =ROUND(SUM(Resumo_Mensal!D4:D15),0) -> 1156604 | E6: =ROUND(SUM(Resumo_Mensal!E4:E15),0) -> 983047 | G6: =ROUND(Resumo_Mensal!G15,0) -> 223557 | I6: =Resumo_Mensal!J15 -> 6.2677272 | K6: =IF(AVERAGE(Resumo_Mensal!E4:E15)=0,0,Resumo_Mensal!G15/AVERAGE(Resumo_Mensal!E4:E15)) -> 2.7289465 | N6: Abr | O6: =Resumo_Mensal!D7 -> 87000 | P6: =Resumo_Mensal!E7 -> 76000 | Q6: =Resumo_Mensal!G7 -> 98500 | R6: =Resumo_Mensal!J7 -> 3.7704678
N7: Mai | O7: =Resumo_Mensal!D8 -> 94000 | P7: =Resumo_Mensal!E8 -> 78500 | Q7: =Resumo_Mensal!G8 -> 114000 | R7: =Resumo_Mensal!J8 -> 4.158528
N8: Jun | O8: =Resumo_Mensal!D9 -> 97000 | P8: =Resumo_Mensal!E9 -> 82000 | Q8: =Resumo_Mensal!G9 -> 129000 | R8: =Resumo_Mensal!J9 -> 4.4159892
N9: Jul | O9: =Resumo_Mensal!D10 -> 101000 | P9: =Resumo_Mensal!E10 -> 84500 | Q9: =Resumo_Mensal!G10 -> 145500 | R9: =Resumo_Mensal!J10 -> 4.7560815
A10: =IF(I6<Premissas!B9,"⚠ LIQUIDEZ ABAIXO DA META","✓ LIQUIDEZ ACIMA DA META") -> ✓ LIQUIDEZ ACIMA DA META | N10: Ago | O10: =Resumo_Mensal!D11 -> 99000 | P10: =Resumo_Mensal!E11 -> 86000 | Q10: =Resumo_Mensal!G11 -> 158500 | R10: =Resumo_Mensal!J11 -> 4.9909561
N11: Set | O11: =Resumo_Mensal!D12 -> 101970 | P11: =Resumo_Mensal!E12 -> 87720 | Q11: =Resumo_Mensal!G12 -> 172750 | R11: =Resumo_Mensal!J12 -> 5.2804251
N12: Out | O12: =Resumo_Mensal!D13 -> 105029.1 | P12: =Resumo_Mensal!E13 -> 89474.4 | Q12: =Resumo_Mensal!G13 -> 188304.7 | R12: =Resumo_Mensal!J13 -> 5.5898021
N13: Nov | O13: =Resumo_Mensal!D14 -> 108179.97 | P13: =Resumo_Mensal!E14 -> 91263.888 | Q13: =Resumo_Mensal!G14 -> 205220.79 | R13: =Resumo_Mensal!J14 -> 5.9189476
N14: Dez | O14: =Resumo_Mensal!D15 -> 111425.37 | P14: =Resumo_Mensal!E15 -> 93089.166 | Q14: =Resumo_Mensal!G15 -> 223556.99 | R14: =Resumo_Mensal!J15 -> 6.2677272
G31: LEITURA GERENCIAL
G32: • Resultado acumulado de 2026:
G33: =ROUND(SUM(Resumo_Mensal!F4:F15),0) -> 173557
G35: • Melhor mês em geração de caixa:
G36: =INDEX(Resumo_Mensal!A4:A15,MATCH(MAX(Resumo_Mensal!F4:F15),Resumo_Mensal!F4:F15,0)) -> 46357
G37: =ROUND(MAX(Resumo_Mensal!F4:F15),0) -> 18336
G38: • Liquidez projetada em dez/26:
G39: =Resumo_Mensal!J15 -> 6.2677272
G41: • Cenário de projeção selecionado:
G42: =Premissas!E7 -> Base
G44: • Caixa cobre aproximadamente:
G45: =K6 -> 2.7289465

Sheet Base_Lancamentos
A1: BASE DE LANÇAMENTOS — REALIZADO
A3: Data | B3: Mês | C3: Tipo | D3: Categoria | E3: Descrição | F3: Valor (R$) | G3: Status | H3: Observação
A4: 46027 | B4: 46023 | C4: Entrada | D4: Receita Operacional | E4: Recebimentos de clientes | F4: 45100 | G4: Realizado
A5: 46034 | B5: 46023 | C5: Entrada | D5: Receita Operacional | E5: Contratos recorrentes | F5: 24600 | G5: Realizado
A6: 46042 | B6: 46023 | C6: Entrada | D6: Outras Receitas | E6: Outras entradas | F6: 12300 | G6: Realizado
A7: 46029 | B7: 46023 | C7: Saída | D7: Pessoal | E7: Folha e encargos | F7: 28560 | G7: Realizado
A8: 46032 | B8: 46023 | C8: Saída | D8: Fornecedores | E8: Pagamentos a fornecedores | F8: 15640 | G8: Realizado
A9: 46037 | B9: 46023 | C9: Saída | D9: Tributos | E9: Impostos e taxas | F9: 13600 | G9: Realizado
A10: 46047 | B10: 46023 | C10: Saída | D10: Despesas Operacionais | E10: Outras despesas operacionais | F10: 10200 | G10: Realizado
A11: 46058 | B11: 46054 | C11: Entrada | D11: Receita Operacional | E11: Recebimentos de clientes | F11: 43450 | G11: Realizado
A12: 46065 | B12: 46054 | C12: Entrada | D12: Receita Operacional | E12: Contratos recorrentes | F12: 23700 | G12: Realizado
A13: 46073 | B13: 46054 | C13: Entrada | D13: Outras Receitas | E13: Outras entradas | F13: 11850 | G13: Realizado
A14: 46060 | B14: 46054 | C14: Saída | D14: Pessoal | E14: Folha e encargos | F14: 30240 | G14: Realizado
A15: 46063 | B15: 46054 | C15: Saída | D15: Fornecedores | E15: Pagamentos a fornecedores | F15: 16560 | G15: Realizado
... A59: 46259 | B59: 46235 | C59: Saída | D59: Despesas Operacionais | E59: Outras despesas operacionais | F59: 12900 | G59: Realizado

Sheet Premissas
A1: PREMISSAS E CENÁRIOS
A3: Premissa | B3: Valor | D3: Cenário | E3: Entradas | F3: Saídas
A4: Saldo inicial de caixa (R$) | B4: 50000 | D4: Conservador | E4: -0.05 | F4: 0.05
A5: Crescimento mensal das entradas | B5: 0.03 | D5: Base | E5: 0 | F5: 0
A6: Crescimento mensal das saídas | B6: 0.02 | D6: Otimista | E6: 0.08 | F6: -0.03
A7: Contas a receber (% entradas) | B7: 0.35 | D7: Cenário selecionado | E7: Base
A8: Contas a pagar (% saídas) | B8: 0.45
A9: Liquidez mínima desejada | B9: 1.2 | D9: Ajuste selecionado | E9: Entradas | F9: Saídas
D10: Valor | E10: =IF(E7="Conservador",E4,IF(E7="Otimista",E6,E5)) -> 0 | F10: =IF(E7="Conservador",F4,IF(E7="Otimista",F6,F5)) -> 0
A11: Como usar
A12: 1. | B12: Altere as premissas amarelas para testar o modelo.
A13: 2. | B13: Escolha um cenário no campo 'Cenário selecionado'.
A14: 3. | B14: O Dashboard e o Resumo Mensal serão atualizados automaticamente.

Sheet Resumo_Mensal
A1: RESUMO MENSAL DE FLUXO DE CAIXA E LIQUIDEZ
A3: Mês | B3: Status | C3: Saldo Inicial (R$) | D3: Entradas (R$) | E3: Saídas (R$) | F3: Resultado (R$) | G3: Saldo Acumulado (R$) | H3: Contas a Receber (R$) | I3: Contas a Pagar (R$) | J3: Liquidez
A4: 46023 | B4: Realizado | C4: =Premissas!B4 -> 50000 | D4: =SUMIFS(Base_Lancamentos!$F$4:$F$59,Base_Lancamentos!$B$4:$B$59,$A4,Base_Lancamentos!$C$4:$C$59,"Entrada") -> 82000 | E4: =SUMIFS(Base_Lancamentos!$F$4:$F$59,Base_Lancamentos!$B$4:$B$59,$A4,Base_Lancamentos!$C$4:$C$59,"Saída") -> 68000 | F4: =D4-E4 -> 14000 | G4: =C4+F4 -> 64000 | H4: =D4*Premissas!$B$7 -> 28700 | I4: =E4*Premissas!$B$8 -> 30600 | J4: =IF(I4=0,0,(G4+H4)/I4) -> 3.0294118
A5: 46054 | B5: Realizado | C5: =G4 -> 64000 | D5: =SUMIFS(Base_Lancamentos!$F$4:$F$59,Base_Lancamentos!$B$4:$B$59,$A5,Base_Lancamentos!$C$4:$C$59,"Entrada") -> 79000 | E5: =SUMIFS(Base_Lancamentos!$F$4:$F$59,Base_Lancamentos!$B$4:$B$59,$A5,Base_Lancamentos!$C$4:$C$59,"Saída") -> 72000 | F5: =D5-E5 -> 7000 | G5: =C5+F5 -> 71000 | H5: =D5*Premissas!$B$7 -> 27650 | I5: =E5*Premissas!$B$8 -> 32400 | J5: =IF(I5=0,0,(G5+H5)/I5) -> 3.0447531
A6: 46082 | B6: Realizado | C6: =G5 -> 71000 | D6: =SUMIFS(Base_Lancamentos!$F$4:$F$59,Base_Lancamentos!$B$4:$B$59,$A6,Base_Lancamentos!$C$4:$C$59,"Entrada") -> 91000 | E6: =SUMIFS(Base_Lancamentos!$F$4:$F$59,Base_Lancamentos!$B$4:$B$59,$A6,Base_Lancamentos!$C$4:$C$59,"Saída") -> 74500 | F6: =D6-E6 -> 16500 | G6: =C6+F6 -> 87500 | H6: =D6*Premissas!$B$7 -> 31850 | I6: =E6*Premissas!$B$8 -> 33525 | J6: =IF(I6=0,0,(G6+H6)/I6) -> 3.5600298
A7: 46113 | B7: Realizado | C7: =G6 -> 87500 | D7: =SUMIFS(Base_Lancamentos!$F$4:$F$59,Base_Lancamentos!$B$4:$B$59,$A7,Base_Lancamentos!$C$4:$C$59,"Entrada") -> 87000 | E7: =SUMIFS(Base_Lancamentos!$F$4:$F$59,Base_Lancamentos!$B$4:$B$59,$A7,Base_Lancamentos!$C$4:$C$59,"Saída") -> 76000 | F7: =D7-E7 -> 11000 | G7: =C7+F7 -> 98500 | H7: =D7*Premissas!$B$7 -> 30450 | I7: =E7*Premissas!$B$8 -> 34200 | J7: =IF(I7=0,0,(G7+H7)/I7) -> 3.7704678
A8: 46143 | B8: Realizado | C8: =G7 -> 98500 | D8: =SUMIFS(Base_Lancamentos!$F$4:$F$59,Base_Lancamentos!$B$4:$B$59,$A8,Base_Lancamentos!$C$4:$C$59,"Entrada") -> 94000 | E8: =SUMIFS(Base_Lancamentos!$F$4:$F$59,Base_Lancamentos!$B$4:$B$59,$A8,Base_Lancamentos!$C$4:$C$59,"Saída") -> 78500 | F8: =D8-E8 -> 15500 | G8: =C8+F8 -> 114000 | H8: =D8*Premissas!$B$7 -> 32900 | I8: =E8*Premissas!$B$8 -> 35325 | J8: =IF(I8=0,0,(G8+H8)/I8) -> 4.158528
A9: 46174 | B9: Realizado | C9: =G8 -> 114000 | D9: =SUMIFS(Base_Lancamentos!$F$4:$F$59,Base_Lancamentos!$B$4:$B$59,$A9,Base_Lancamentos!$C$4:$C$59,"Entrada") -> 97000 | E9: =SUMIFS(Base_Lancamentos!$F$4:$F$59,Base_Lancamentos!$B$4:$B$59,$A9,Base_Lancamentos!$C$4:$C$59,"Saída") -> 82000 | F9: =D9-E9 -> 15000 | G9: =C9+F9 -> 129000 | H9: =D9*Premissas!$B$7 -> 33950 | I9: =E9*Premissas!$B$8 -> 36900 | J9: =IF(I9=0,0,(G9+H9)/I9) -> 4.4159892
A10: 46204 | B10: Realizado | C10: =G9 -> 129000 | D10: =SUMIFS(Base_Lancamentos!$F$4:$F$59,Base_Lancamentos!$B$4:$B$59,$A10,Base_Lancamentos!$C$4:$C$59,"Entrada") -> 101000 | E10: =SUMIFS(Base_Lancamentos!$F$4:$F$59,Base_Lancamentos!$B$4:$B$59,$A10,Base_Lancamentos!$C$4:$C$59,"Saída") -> 84500 | F10: =D10-E10 -> 16500 | G10: =C10+F10 -> 145500 | H10: =D10*Premissas!$B$7 -> 35350 | I10: =E10*Premissas!$B$8 -> 38025 | J10: =IF(I10=0,0,(G10+H10)/I10) -> 4.7560815
A11: 46235 | B11: Realizado | C11: =G10 -> 145500 | D11: =SUMIFS(Base_Lancamentos!$F$4:$F$59,Base_Lancamentos!$B$4:$B$59,$A11,Base_Lancamentos!$C$4:$C$59,"Entrada") -> 99000 | E11: =SUMIFS(Base_Lancamentos!$F$4:$F$59,Base_Lancamentos!$B$4:$B$59,$A11,Base_Lancamentos!$C$4:$C$59,"Saída") -> 86000 | F11: =D11-E11 -> 13000 | G11: =C11+F11 -> 158500 | H11: =D11*Premissas!$B$7 -> 34650 | I11: =E11*Premissas!$B$8 -> 38700 | J11: =IF(I11=0,0,(G11+H11)/I11) -> 4.9909561
A12: 46266 | B12: Projetado | C12: =G11 -> 158500 | D12: =D11*(1+Premissas!$B$5+Premissas!$E$10) -> 101970 | E12: =E11*(1+Premissas!$B$6+Premissas!$F$10) -> 87720 | F12: =D12-E12 -> 14250 | G12: =C12+F12 -> 172750 | H12: =D12*Premissas!$B$7 -> 35689.5 | I12: =E12*Premissas!$B$8 -> 39474 | J12: =IF(I12=0,0,(G12+H12)/I12) -> 5.2804251
A13: 46296 | B13: Projetado | C13: =G12 -> 172750 | D13: =D12*(1+Premissas!$B$5+Premissas!$E$10) -> 105029.1 | E13: =E12*(1+Premissas!$B$6+Premissas!$F$10) -> 89474.4 | F13: =D13-E13 -> 15554.7 | G13: =C13+F13 -> 188304.7 | H13: =D13*Premissas!$B$7 -> 36760.185 | I13: =E13*Premissas!$B$8 -> 40263.48 | J13: =IF(I13=0,0,(G13+H13)/I13) -> 5.5898021
A14: 46327 | B14: Projetado | C14: =G13 -> 188304.7 | D14: =D13*(1+Premissas!$B$5+Premissas!$E$10) -> 108179.97 | E14: =E13*(1+Premissas!$B$6+Premissas!$F$10) -> 91263.888 | F14: =D14-E14 -> 16916.085 | G14: =C14+F14 -> 205220.79 | H14: =D14*Premissas!$B$7 -> 37862.991 | I14: =E14*Premissas!$B$8 -> 41068.75 | J14: =IF(I14=0,0,(G14+H14)/I14) -> 5.9189476
A15: 46357 | B15: Projetado | C15: =G14 -> 205220.79 | D15: =D14*(1+Premissas!$B$5+Premissas!$E$10) -> 111425.37 | E15: =E14*(1+Premissas!$B$6+Premissas!$F$10) -> 93089.166 | F15: =D15-E15 -> 18336.206 | G15: =C15+F15 -> 223556.99 | H15: =D15*Premissas!$B$7 -> 38998.88 | I15: =E15*Premissas!$B$8 -> 41890.125 | J15: =IF(I15=0,0,(G15+H15)/I15) -> 6.2677272

Sheet Premissas_V2
A1: PREMISSAS — MODELO FP&A V2
A3: Premissa | B3: Valor | C3: Uso no modelo
A4: Mês de fechamento realizado | B4: 8 | C4: Jan–Ago = realizado; Set–Dez = forecast
A5: Crescimento Receita Operacional | B5: 0.03 | C5: Forecast mensal após agosto
A6: Crescimento Outras Receitas | B6: 0.01 | C6: Forecast mensal após agosto
A7: Crescimento Fornecedores | B7: 0.02 | C7: Forecast mensal após agosto
A8: Crescimento Pessoal | B8: 0.015 | C8: Forecast mensal após agosto
A9: Crescimento Tributos | B9: 0.018 | C9: Forecast mensal após agosto
A10: Crescimento Desp. Operacionais | B10: 0.012 | C10: Forecast mensal após agosto
A11: Meta Margem EBITDA | B11: 0.18 | C11: Indicador gerencial
A12: Meta Liquidez | B12: 1.2 | C12: Indicador de caixa
A14: Convenção: células amarelas/azuis = premissas editáveis. O forecast e os painéis são recalculados automaticamente.

Sheet Orcado_Forecast
A1: ORÇADO x REALIZADO x FORECAST — BASE MENSAL
A3: Mês | B3: Categoria | C3: Tipo | D3: Orçado (R$) | E3: Realizado (R$) | F3: Forecast (R$) | G3: Var Fct x Orç (R$) | H3: Var Fct x Orç (%)
A4: 46023 | B4: Receita Operacional | C4: Receita | D4: 70000 | E4: =SUMIFS(Base_Lancamentos!$F$4:$F$59,Base_Lancamentos!$B$4:$B$59,$A4,Base_Lancamentos!$D$4:$D$59,$B4) -> 69700 | F4: =E4 -> 69700 | G4: =F4-D4 -> -300 | H4: =IF(D4=0,0,G4/D4) -> -0.0042857143
A5: 46023 | B5: Outras Receitas | C5: Receita | D5: 12500 | E5: =SUMIFS(Base_Lancamentos!$F$4:$F$59,Base_Lancamentos!$B$4:$B$59,$A5,Base_Lancamentos!$D$4:$D$59,$B5) -> 12300 | F5: =E5 -> 12300 | G5: =F5-D5 -> -200 | H5: =IF(D5=0,0,G5/D5) -> -0.016
A6: 46023 | B6: Fornecedores | C6: Despesa | D6: 16500 | E6: =SUMIFS(Base_Lancamentos!$F$4:$F$59,Base_Lancamentos!$B$4:$B$59,$A6,Base_Lancamentos!$D$4:$D$59,$B6) -> 15640 | F6: =E6 -> 15640 | G6: =F6-D6 -> -860 | H6: =IF(D6=0,0,G6/D6) -> -0.052121212
A7: 46023 | B7: Pessoal | C7: Despesa | D7: 30000 | E7: =SUMIFS(Base_Lancamentos!$F$4:$F$59,Base_Lancamentos!$B$4:$B$59,$A7,Base_Lancamentos!$D$4:$D$59,$B7) -> 28560 | F7: =E7 -> 28560 | G7: =F7-D7 -> -1440 | H7: =IF(D7=0,0,G7/D7) -> -0.048
A8: 46023 | B8: Tributos | C8: Despesa | D8: 14500 | E8: =SUMIFS(Base_Lancamentos!$F$4:$F$59,Base_Lancamentos!$B$4:$B$59,$A8,Base_Lancamentos!$D$4:$D$59,$B8) -> 13600 | F8: =E8 -> 13600 | G8: =F8-D8 -> -900 | H8: =IF(D8=0,0,G8/D8) -> -0.062068966
A9: 46023 | B9: Despesas Operacionais | C9: Despesa | D9: 11000 | E9: =SUMIFS(Base_Lancamentos!$F$4:$F$59,Base_Lancamentos!$B$4:$B$59,$A9,Base_Lancamentos!$D$4:$D$59,$B9) -> 10200 | F9: =E9 -> 10200 | G9: =F9-D9 -> -800 | H9: =IF(D9=0,0,G9/D9) -> -0.072727273
A10: 46054 | B10: Receita Operacional | C10: Receita | D10: 71260 | E10: =SUMIFS(Base_Lancamentos!$F$4:$F$59,Base_Lancamentos!$B$4:$B$59,$A10,Base_Lancamentos!$D$4:$D$59,$B10) -> 67150 | F10: =E10 -> 67150 | G10: =F10-D10 -> -4110 | H10: =IF(D10=0,0,G10/D10) -> -0.057676116
A11: 46054 | B11: Outras Receitas | C11: Receita | D11: 12562.5 | E11: =SUMIFS(Base_Lancamentos!$F$4:$F$59,Base_Lancamentos!$B$4:$B$59,$A11,Base_Lancamentos!$D$4:$D$59,$B11) -> 11850 | F11: =E11 -> 11850 | G11: =F11-D11 -> -712.5 | H11: =IF(D11=0,0,G11/D11) -> -0.056716418
A12: 46054 | B12: Fornecedores | C12: Despesa | D12: 16665 | E12: =SUMIFS(Base_Lancamentos!$F$4:$F$59,Base_Lancamentos!$B$4:$B$59,$A12,Base_Lancamentos!$D$4:$D$59,$B12) -> 16560 | F12: =E12 -> 16560 | G12: =F12-D12 -> -105 | H12: =IF(D12=0,0,G12/D12) -> -0.0063006301
A13: 46054 | B13: Pessoal | C13: Despesa | D13: 30240 | E13: =SUMIFS(Base_Lancamentos!$F$4:$F$59,Base_Lancamentos!$B$4:$B$59,$A13,Base_Lancamentos!$D$4:$D$59,$B13) -> 30240 | F13: =E13 -> 30240 | G13: =F13-D13 -> 0 | H13: =IF(D13=0,0,G13/D13) -> 0
A14: 46054 | B14: Tributos | C14: Despesa | D14: 14645 | E14: =SUMIFS(Base_Lancamentos!$F$4:$F$59,Base_Lancamentos!$B$4:$B$59,$A14,Base_Lancamentos!$D$4:$D$59,$B14) -> 14400 | F14: =E14 -> 14400 | G14: =F14-D14 -> -245 | H14: =IF(D14=0,0,G14/D14) -> -0.016729259
A15: 46054 | B15: Despesas Operacionais | C15: Despesa | D15: 11066 | E15: =SUMIFS(Base_Lancamentos!$F$4:$F$59,Base_Lancamentos!$B$4:$B$59,$A15,Base_Lancamentos!$D$4:$D$59,$B15) -> 10800 | F15: =E15 -> 10800 | G15: =F15-D15 -> -266 | H15: =IF(D15=0,0,G15/D15) -> -0.024037593
... A51: 46235 | B51: Despesas Operacionais | C51: Despesa | D51: 11470.4 | E51: =SUMIFS(Base_Lancamentos!$F$4:$F$59,Base_Lancamentos!$B$4:$B$59,$A51,Base_Lancamentos!$D$4:$D$59,$B51) -> 12900 | F51: =E51 -> 12900 | G51: =F51-D51 -> 1429.6 | H51: =IF(D51=0,0,G51/D51) -> 0.12463384
A52: 46266 | B52: Receita Operacional | C52: Receita | D52: 80738.42 | E52: =SUMIFS(Base_Lancamentos!$F$4:$F$59,Base_Lancamentos!$B$4:$B$59,$A52,Base_Lancamentos!$D$4:$D$59,$B52) -> 0 | F52: =F46*(1+Premissas_V2!$B$5) -> 86674.5 | G52: =F52-D52 -> 5936.08 | H52: =IF(D52=0,0,G52/D52) -> 0.07352237
A53: 46266 | B53: Outras Receitas | C53: Receita | D53: 13008.84 | E53: =SUMIFS(Base_Lancamentos!$F$4:$F$59,Base_Lancamentos!$B$4:$B$59,$A53,Base_Lancamentos!$D$4:$D$59,$B53) -> 0 | F53: =F47*(1+Premissas_V2!$B$6) -> 14998.5 | G53: =F53-D53 -> 1989.66 | H53: =IF(D53=0,0,G53/D53) -> 0.15294677
A54: 46266 | B54: Fornecedores | C54: Despesa | D54: 17867.14 | E54: =SUMIFS(Base_Lancamentos!$F$4:$F$59,Base_Lancamentos!$B$4:$B$59,$A54,Base_Lancamentos!$D$4:$D$59,$B54) -> 0 | F54: =F48*(1+Premissas_V2!$B$7) -> 20175.6 | G54: =F54-D54 -> 2308.46 | H54: =IF(D54=0,0,G54/D54) -> 0.12920143
A55: 46266 | B55: Pessoal | C55: Despesa | D55: 31974.63 | E55: =SUMIFS(Base_Lancamentos!$F$4:$F$59,Base_Lancamentos!$B$4:$B$59,$A55,Base_Lancamentos!$D$4:$D$59,$B55) -> 0 | F55: =F49*(1+Premissas_V2!$B$8) -> 36661.8 | G55: =F55-D55 -> 4687.17 | H55: =IF(D55=0,0,G55/D55) -> 0.14659028
A56: 46266 | B56: Tributos | C56: Despesa | D56: 15701.42 | E56: =SUMIFS(Base_Lancamentos!$F$4:$F$59,Base_Lancamentos!$B$4:$B$59,$A56,Base_Lancamentos!$D$4:$D$59,$B56) -> 0 | F56: =F50*(1+Premissas_V2!$B$9) -> 17509.6 | G56: =F56-D56 -> 1808.18 | H56: =IF(D56=0,0,G56/D56) -> 0.11516028
A57: 46266 | B57: Despesas Operacionais | C57: Despesa | D57: 11539.22 | E57: =SUMIFS(Base_Lancamentos!$F$4:$F$59,Base_Lancamentos!$B$4:$B$59,$A57,Base_Lancamentos!$D$4:$D$59,$B57) -> 0 | F57: =F51*(1+Premissas_V2!$B$10) -> 13054.8 | G57: =F57-D57 -> 1515.58 | H57: =IF(D57=0,0,G57/D57) -> 0.13134163
A58: 46296 | B58: Receita Operacional | C58: Receita | D58: 82191.71 | E58: =SUMIFS(Base_Lancamentos!$F$4:$F$59,Base_Lancamentos!$B$4:$B$59,$A58,Base_Lancamentos!$D$4:$D$59,$B58) -> 0 | F58: =F52*(1+Premissas_V2!$B$5) -> 89274.735 | G58: =F58-D58 -> 7083.025 | H58: =IF(D58=0,0,G58/D58) -> 0.086176878
A59: 46296 | B59: Outras Receitas | C59: Receita | D59: 13073.88 | E59: =SUMIFS(Base_Lancamentos!$F$4:$F$59,Base_Lancamentos!$B$4:$B$59,$A59,Base_Lancamentos!$D$4:$D$59,$B59) -> 0 | F59: =F53*(1+Premissas_V2!$B$6) -> 15148.485 | G59: =F59-D59 -> 2074.605 | H59: =IF(D59=0,0,G59/D59) -> 0.15868319
A60: 46296 | B60: Fornecedores | C60: Despesa | D60: 18045.81 | E60: =SUMIFS(Base_Lancamentos!$F$4:$F$59,Base_Lancamentos!$B$4:$B$59,$A60,Base_Lancamentos!$D$4:$D$59,$B60) -> 0 | F60: =F54*(1+Premissas_V2!$B$7) -> 20579.112 | G60: =F60-D60 -> 2533.302 | H60: =IF(D60=0,0,G60/D60) -> 0.14038173
A61: 46296 | B61: Pessoal | C61: Despesa | D61: 32230.43 | E61: =SUMIFS(Base_Lancamentos!$F$4:$F$59,Base_Lancamentos!$B$4:$B$59,$A61,Base_Lancamentos!$D$4:$D$59,$B61) -> 0 | F61: =F55*(1+Premissas_V2!$B$8) -> 37211.727 | G61: =F61-D61 -> 4981.297 | H61: =IF(D61=0,0,G61/D61) -> 0.15455261
A62: 46296 | B62: Tributos | C62: Despesa | D62: 15858.44 | E62: =SUMIFS(Base_Lancamentos!$F$4:$F$59,Base_Lancamentos!$B$4:$B$59,$A62,Base_Lancamentos!$D$4:$D$59,$B62) -> 0 | F62: =F56*(1+Premissas_V2!$B$9) -> 17824.773 | G62: =F62-D62 -> 1966.3328 | H62: =IF(D62=0,0,G62/D62) -> 0.12399283
A63: 46296 | B63: Despesas Operacionais | C63: Despesa | D63: 11608.46 | E63: =SUMIFS(Base_Lancamentos!$F$4:$F$59,Base_Lancamentos!$B$4:$B$59,$A63,Base_Lancamentos!$D$4:$D$59,$B63) -> 0 | F63: =F57*(1+Premissas_V2!$B$10) -> 13211.458 | G63: =F63-D63 -> 1602.9976 | H63: =IF(D63=0,0,G63/D63) -> 0.13808874
A64: 46327 | B64: Receita Operacional | C64: Receita | D64: 83671.17 | E64: =SUMIFS(Base_Lancamentos!$F$4:$F$59,Base_Lancamentos!$B$4:$B$59,$A64,Base_Lancamentos!$D$4:$D$59,$B64) -> 0 | F64: =F58*(1+Premissas_V2!$B$5) -> 91952.977 | G64: =F64-D64 -> 8281.8071 | H64: =IF(D64=0,0,G64/D64) -> 0.098980414
A65: 46327 | B65: Outras Receitas | C65: Receita | D65: 13139.25 | E65: =SUMIFS(Base_Lancamentos!$F$4:$F$59,Base_Lancamentos!$B$4:$B$59,$A65,Base_Lancamentos!$D$4:$D$59,$B65) -> 0 | F65: =F59*(1+Premissas_V2!$B$6) -> 15299.97 | G65: =F65-D65 -> 2160.7199 | H65: =IF(D65=0,0,G65/D65) -> 0.16444773
A66: 46327 | B66: Fornecedores | C66: Despesa | D66: 18226.27 | E66: =SUMIFS(Base_Lancamentos!$F$4:$F$59,Base_Lancamentos!$B$4:$B$59,$A66,Base_Lancamentos!$D$4:$D$59,$B66) -> 0 | F66: =F60*(1+Premissas_V2!$B$7) -> 20990.694 | G66: =F66-D66 -> 2764.4242 | H66: =IF(D66=0,0,G66/D66) -> 0.15167252
A67: 46327 | B67: Pessoal | C67: Despesa | D67: 32488.27 | E67: =SUMIFS(Base_Lancamentos!$F$4:$F$59,Base_Lancamentos!$B$4:$B$59,$A67,Base_Lancamentos!$D$4:$D$59,$B67) -> 0 | F67: =F61*(1+Premissas_V2!$B$8) -> 37769.903 | G67: =F67-D67 -> 5281.6329 | H67: =IF(D67=0,0,G67/D67) -> 0.16257046
A68: 46327 | B68: Tributos | C68: Despesa | D68: 16017.02 | E68: =SUMIFS(Base_Lancamentos!$F$4:$F$59,Base_Lancamentos!$B$4:$B$59,$A68,Base_Lancamentos!$D$4:$D$59,$B68) -> 0 | F68: =F62*(1+Premissas_V2!$B$9) -> 18145.619 | G68: =F68-D68 -> 2128.5987 | H68: =IF(D68=0,0,G68/D68) -> 0.13289605
A69: 46327 | B69: Despesas Operacionais | C69: Despesa | D69: 11678.11 | E69: =SUMIFS(Base_Lancamentos!$F$4:$F$59,Base_Lancamentos!$B$4:$B$59,$A69,Base_Lancamentos!$D$4:$D$59,$B69) -> 0 | F69: =F63*(1+Premissas_V2!$B$10) -> 13369.995 | G69: =F69-D69 -> 1691.8851 | H69: =IF(D69=0,0,G69/D69) -> 0.14487662
A70: 46357 | B70: Receita Operacional | C70: Receita | D70: 85177.25 | E70: =SUMIFS(Base_Lancamentos!$F$4:$F$59,Base_Lancamentos!$B$4:$B$59,$A70,Base_Lancamentos!$D$4:$D$59,$B70) -> 0 | F70: =F64*(1+Premissas_V2!$B$5) -> 94711.566 | G70: =F70-D70 -> 9534.3164 | H70: =IF(D70=0,0,G70/D70) -> 0.11193501
A71: 46357 | B71: Outras Receitas | C71: Receita | D71: 13204.95 | E71: =SUMIFS(Base_Lancamentos!$F$4:$F$59,Base_Lancamentos!$B$4:$B$59,$A71,Base_Lancamentos!$D$4:$D$59,$B71) -> 0 | F71: =F65*(1+Premissas_V2!$B$6) -> 15452.97 | G71: =F71-D71 -> 2248.0195 | H71: =IF(D71=0,0,G71/D71) -> 0.17024067
A72: 46357 | B72: Fornecedores | C72: Despesa | D72: 18408.53 | E72: =SUMIFS(Base_Lancamentos!$F$4:$F$59,Base_Lancamentos!$B$4:$B$59,$A72,Base_Lancamentos!$D$4:$D$59,$B72) -> 0 | F72: =F66*(1+Premissas_V2!$B$7) -> 21410.508 | G72: =F72-D72 -> 3001.9781 | H72: =IF(D72=0,0,G72/D72) -> 0.16307539
A73: 46357 | B73: Pessoal | C73: Despesa | D73: 32748.18 | E73: =SUMIFS(Base_Lancamentos!$F$4:$F$59,Base_Lancamentos!$B$4:$B$59,$A73,Base_Lancamentos!$D$4:$D$59,$B73) -> 0 | F73: =F67*(1+Premissas_V2!$B$8) -> 38336.451 | G73: =F73-D73 -> 5588.2714 | H73: =IF(D73=0,0,G73/D73) -> 0.17064373
A74: 46357 | B74: Tributos | C74: Despesa | D74: 16177.19 | E74: =SUMIFS(Base_Lancamentos!$F$4:$F$59,Base_Lancamentos!$B$4:$B$59,$A74,Base_Lancamentos!$D$4:$D$59,$B74) -> 0 | F74: =F68*(1+Premissas_V2!$B$9) -> 18472.24 | G74: =F74-D74 -> 2295.0498 | H74: =IF(D74=0,0,G74/D74) -> 0.1418695
A75: 46357 | B75: Despesas Operacionais | C75: Despesa | D75: 11748.18 | E75: =SUMIFS(Base_Lancamentos!$F$4:$F$59,Base_Lancamentos!$B$4:$B$59,$A75,Base_Lancamentos!$D$4:$D$59,$B75) -> 0 | F75: =F69*(1+Premissas_V2!$B$10) -> 13530.435 | G75: =F75-D75 -> 1782.255 | H75: =IF(D75=0,0,G75/D75) -> 0.15170478

Sheet DRE_Gerencial
A1: DRE GERENCIAL — ORÇADO, REALIZADO E FORECAST 2026
A3: Linha DRE | B3: Jan | C3: Fev | D3: Mar | E3: Abr | F3: Mai | G3: Jun | H3: Jul | I3: Ago | J3: Set | K3: Out | L3: Nov | M3: Dez | N3: Orçado FY | O3: Forecast FY | P3: Var. R$ | Q3: Var. %
A4: Receita Operacional | B4: =Orcado_Forecast!F4 -> 69700 | C4: =Orcado_Forecast!F10 -> 67150 | D4: =Orcado_Forecast!F16 -> 77350 | E4: =Orcado_Forecast!F22 -> 73950 | F4: =Orcado_Forecast!F28 -> 79900 | G4: =Orcado_Forecast!F34 -> 82450 | H4: =Orcado_Forecast!F40 -> 85850 | I4: =Orcado_Forecast!F46 -> 84150 | J4: =Orcado_Forecast!F52 -> 86674.5 | K4: =Orcado_Forecast!F58 -> 89274.735 | L4: =Orcado_Forecast!F64 -> 91952.977 | M4: =Orcado_Forecast!F70 -> 94711.566 | N4: =SUMIFS(Orcado_Forecast!$D$4:$D$75,Orcado_Forecast!$B$4:$B$75,"Receita Operacional") -> 928357.63 | O4: =SUMIFS(Orcado_Forecast!$F$4:$F$75,Orcado_Forecast!$B$4:$B$75,"Receita Operacional") -> 983113.78 | P4: =O4-N4 -> 54756.148 | Q4: =IF(N4=0,0,P4/ABS(N4)) -> 0.05898174
A5: Outras Receitas | B5: =Orcado_Forecast!F5 -> 12300 | C5: =Orcado_Forecast!F11 -> 11850 | D5: =Orcado_Forecast!F17 -> 13650 | E5: =Orcado_Forecast!F23 -> 13050 | F5: =Orcado_Forecast!F29 -> 14100 | G5: =Orcado_Forecast!F35 -> 14550 | H5: =Orcado_Forecast!F41 -> 15150 | I5: =Orcado_Forecast!F47 -> 14850 | J5: =Orcado_Forecast!F53 -> 14998.5 | K5: =Orcado_Forecast!F59 -> 15148.485 | L5: =Orcado_Forecast!F65 -> 15299.97 | M5: =Orcado_Forecast!F71 -> 15452.97 | N5: =SUMIFS(Orcado_Forecast!$D$4:$D$75,Orcado_Forecast!$B$4:$B$75,"Outras Receitas") -> 154194.53 | O5: =SUMIFS(Orcado_Forecast!$F$4:$F$75,Orcado_Forecast!$B$4:$B$75,"Outras Receitas") -> 170399.92 | P5: =O5-N5 -> 16205.394 | Q5: =IF(N5=0,0,P5/ABS(N5)) -> 0.10509708
A6: Receita Total | B6: =B4+B5 -> 82000 | C6: =C4+C5 -> 79000 | D6: =D4+D5 -> 91000 | E6: =E4+E5 -> 87000 | F6: =F4+F5 -> 94000 | G6: =G4+G5 -> 97000 | H6: =H4+H5 -> 101000 | I6: =I4+I5 -> 99000 | ... O6: =O4+O5 -> 1153513.7 | P6: =O6-N6 -> 70961.543 | Q6: =IF(N6=0,0,P6/ABS(N6)) -> 0.06555023
A7: (-) Fornecedores / Custos Diretos | B7: =-Orcado_Forecast!F6 -> -15640 | C7: =-Orcado_Forecast!F12 -> -16560 | D7: =-Orcado_Forecast!F18 -> -17135 | E7: =-Orcado_Forecast!F24 -> -17480 | F7: =-Orcado_Forecast!F30 -> -18055 | G7: =-Orcado_Forecast!F36 -> -18860 | H7: =-Orcado_Forecast!F42 -> -19435 | I7: =-Orcado_Forecast!F48 -> -19780 | J7: =-Orcado_Forecast!F54 -> -20175.6 | K7: =-Orcado_Forecast!F60 -> -20579.112 | L7: =-Orcado_Forecast!F66 -> -20990.694 | M7: =-Orcado_Forecast!F72 -> -21410.508 | N7: =-SUMIFS(Orcado_Forecast!$D$4:$D$75,Orcado_Forecast!$B$4:$B$75,"Fornecedores") -> -209261.32 | O7: =-SUMIFS(Orcado_Forecast!$F$4:$F$75,Orcado_Forecast!$B$4:$B$75,"Fornecedores") -> -226100.91 | P7: =O7-N7 -> -16839.594 | Q7: =IF(N7=0,0,P7/ABS(N7)) -> -0.080471605
A8: Margem Bruta | B8: =B6+B7 -> 66360 | C8: =C6+C7 -> 62440 | D8: =D6+D7 -> 73865 | E8: =E6+E7 -> 69520 | F8: =F6+F7 -> 75945 | G8: =G6+G7 -> 78140 | H8: =H6+H7 -> 81565 | I8: =I6+I7 -> 79220 | ... O8: =O6+O7 -> 927412.79 | P8: =O8-N8 -> 54121.948 | Q8: =IF(N8=0,0,P8/ABS(N8)) -> 0.061974712
A9: (-) Pessoal | B9: =-Orcado_Forecast!F7 -> -28560 | C9: =-Orcado_Forecast!F13 -> -30240 | D9: =-Orcado_Forecast!F19 -> -31290 | E9: =-Orcado_Forecast!F25 -> -31920 | F9: =-Orcado_Forecast!F31 -> -32970 | G9: =-Orcado_Forecast!F37 -> -34440 | H9: =-Orcado_Forecast!F43 -> -35490 | I9: =-Orcado_Forecast!F49 -> -36120 | J9: =-Orcado_Forecast!F55 -> -36661.8 | K9: =-Orcado_Forecast!F61 -> -37211.727 | L9: =-Orcado_Forecast!F67 -> -37769.903 | M9: =-Orcado_Forecast!F73 -> -38336.451 | N9: =-SUMIFS(Orcado_Forecast!$D$4:$D$75,Orcado_Forecast!$B$4:$B$75,"Pessoal") -> -376270.11 | O9: =-SUMIFS(Orcado_Forecast!$F$4:$F$75,Orcado_Forecast!$B$4:$B$75,"Pessoal") -> -411009.88 | P9: =O9-N9 -> -34739.771 | Q9: =IF(N9=0,0,P9/ABS(N9)) -> -0.092326683
A10: (-) Tributos | B10: =-Orcado_Forecast!F8 -> -13600 | C10: =-Orcado_Forecast!F14 -> -14400 | D10: =-Orcado_Forecast!F20 -> -14900 | E10: =-Orcado_Forecast!F26 -> -15200 | F10: =-Orcado_Forecast!F32 -> -15700 | G10: =-Orcado_Forecast!F38 -> -16400 | H10: =-Orcado_Forecast!F44 -> -16900 | I10: =-Orcado_Forecast!F50 -> -17200 | J10: =-Orcado_Forecast!F56 -> -17509.6 | K10: =-Orcado_Forecast!F62 -> -17824.773 | L10: =-Orcado_Forecast!F68 -> -18145.619 | M10: =-Orcado_Forecast!F74 -> -18472.24 | N10: =-SUMIFS(Orcado_Forecast!$D$4:$D$75,Orcado_Forecast!$B$4:$B$75,"Tributos") -> -183896.29 | O10: =-SUMIFS(Orcado_Forecast!$F$4:$F$75,Orcado_Forecast!$B$4:$B$75,"Tributos") -> -196252.23 | P10: =O10-N10 -> -12355.941 | Q10: =IF(N10=0,0,P10/ABS(N10)) -> -0.067189726
A11: (-) Despesas Operacionais | B11: =-Orcado_Forecast!F9 -> -10200 | C11: =-Orcado_Forecast!F15 -> -10800 | D11: =-Orcado_Forecast!F21 -> -11175 | E11: =-Orcado_Forecast!F27 -> -11400 | F11: =-Orcado_Forecast!F33 -> -11775 | G11: =-Orcado_Forecast!F39 -> -12300 | H11: =-Orcado_Forecast!F45 -> -12675 | I11: =-Orcado_Forecast!F51 -> -12900 | J11: =-Orcado_Forecast!F57 -> -13054.8 | K11: =-Orcado_Forecast!F63 -> -13211.458 | L11: =-Orcado_Forecast!F69 -> -13369.995 | M11: =-Orcado_Forecast!F75 -> -13530.435 | N11: =-SUMIFS(Orcado_Forecast!$D$4:$D$75,Orcado_Forecast!$B$4:$B$75,"Despesas Operacionais") -> -136444.32 | O11: =-SUMIFS(Orcado_Forecast!$F$4:$F$75,Orcado_Forecast!$B$4:$B$75,"Despesas Operacionais") -> -146391.69 | P11: =O11-N11 -> -9947.3677 | Q11: =IF(N11=0,0,P11/ABS(N11)) -> -0.072904227
A12: EBITDA Gerencial | B12: =SUM(B8:B11) -> 14000 | C12: =SUM(C8:C11) -> 7000 | D12: =SUM(D8:D11) -> 16500 | E12: =SUM(E8:E11) -> 11000 | F12: =SUM(F8:F11) -> 15500 | G12: =SUM(G8:G11) -> 15000 | H12: =SUM(H8:H11) -> 16500 | I12: =SUM(I8:I11) -> 13000 | ... O12: =SUM(O8:O11) -> 173758.99 | P12: =O12-N12 -> -2921.132 | Q12: =IF(N12=0,0,P12/ABS(N12)) -> -0.01653345
A13: Margem EBITDA | B13: =IF(B6=0,0,B12/B6) -> 0.17073171 | C13: =IF(C6=0,0,C12/C6) -> 0.088607595 | D13: =IF(D6=0,0,D12/D6) -> 0.18131868 | E13: =IF(E6=0,0,E12/E6) -> 0.12643678 | F13: =IF(F6=0,0,F12/F6) -> 0.16489362 | G13: =IF(G6=0,0,G12/G6) -> 0.15463918 | H13: =IF(H6=0,0,H12/H6) -> 0.16336634 | I13: =IF(I6=0,0,I12/I6) -> 0.13131313 | ... O13: =IF(O6=0,0,O12/O6) -> 0.15063452 | P13: =O13-N13 -> -0.012572503 | Q13: =P13 -> -0.012572503

Sheet Analise_Desvios
A1: ANÁLISE DE DESVIOS — FORECAST x ORÇADO
A3: Categoria | B3: Orçado FY (R$) | C3: Forecast FY (R$) | D3: Desvio (R$) | E3: Desvio (%) | F3: Impacto | G3: Comentário gerencial | H3: Prioridade
A4: Receita Operacional | B4: =DRE_Gerencial!N4 -> 928357.63 | C4: =DRE_Gerencial!O4 -> 983113.78 | D4: =C4-B4 -> 54756.148 | E4: =IF(B4=0,0,D4/B4) -> 0.05898174 | F4: =IF(D4>=0,"Favorável","Desfavorável") -> Favorável | G4: =IF(D4>=0,"Receita acima do orçamento: investigar drivers positivos e sustentabilidade.","Receita abaixo do orçamento: revisar volume, preço, mix e timing de recebimentos.") -> Receita acima do orçamento: investigar drivers positivos e sustentabilidade. | H4: =IF(ABS(E4)>=0.1,"Alta",IF(ABS(E4)>=0.05,"Média","Baixa")) -> Média
A5: Outras Receitas | B5: =DRE_Gerencial!N5 -> 154194.53 | C5: =DRE_Gerencial!O5 -> 170399.92 | D5: =C5-B5 -> 16205.394 | E5: =IF(B5=0,0,D5/B5) -> 0.10509708 | F5: =IF(D5>=0,"Favorável","Desfavorável") -> Favorável | G5: =IF(D5>=0,"Receita acima do orçamento: investigar drivers positivos e sustentabilidade.","Receita abaixo do orçamento: revisar volume, preço, mix e timing de recebimentos.") -> Receita acima do orçamento: investigar drivers positivos e sustentabilidade. | H5: =IF(ABS(E5)>=0.1,"Alta",IF(ABS(E5)>=0.05,"Média","Baixa")) -> Alta
A6: Fornecedores | B6: =-DRE_Gerencial!N7 -> 209261.32 | C6: =-DRE_Gerencial!O7 -> 226100.91 | D6: =C6-B6 -> 16839.594 | E6: =IF(B6=0,0,D6/B6) -> 0.080471605 | F6: =IF(D6<=0,"Favorável","Desfavorável") -> Desfavorável | G6: =IF(D6<=0,"Despesa abaixo do orçamento: validar economia e possíveis postergações.","Despesa acima do orçamento: revisar causa, recorrência e plano de ação.") -> Despesa acima do orçamento: revisar causa, recorrência e plano de ação. | H6: =IF(ABS(E6)>=0.1,"Alta",IF(ABS(E6)>=0.05,"Média","Baixa")) -> Média
A7: Pessoal | B7: =-DRE_Gerencial!N9 -> 376270.11 | C7: =-DRE_Gerencial!O9 -> 411009.88 | D7: =C7-B7 -> 34739.771 | E7: =IF(B7=0,0,D7/B7) -> 0.092326683 | F7: =IF(D7<=0,"Favorável","Desfavorável") -> Desfavorável | G7: =IF(D7<=0,"Despesa abaixo do orçamento: validar economia e possíveis postergações.","Despesa acima do orçamento: revisar causa, recorrência e plano de ação.") -> Despesa acima do orçamento: revisar causa, recorrência e plano de ação. | H7: =IF(ABS(E7)>=0.1,"Alta",IF(ABS(E7)>=0.05,"Média","Baixa")) -> Média
A8: Tributos | B8: =-DRE_Gerencial!N10 -> 183896.29 | C8: =-DRE_Gerencial!O10 -> 196252.23 | D8: =C8-B8 -> 12355.941 | E8: =IF(B8=0,0,D8/B8) -> 0.067189726 | F8: =IF(D8<=0,"Favorável","Desfavorável") -> Desfavorável | G8: =IF(D8<=0,"Despesa abaixo do orçamento: validar economia e possíveis postergações.","Despesa acima do orçamento: revisar causa, recorrência e plano de ação.") -> Despesa acima do orçamento: revisar causa, recorrência e plano de ação. | H8: =IF(ABS(E8)>=0.1,"Alta",IF(ABS(E8)>=0.05,"Média","Baixa")) -> Média
A9: Despesas Operacionais | B9: =-DRE_Gerencial!N11 -> 136444.32 | C9: =-DRE_Gerencial!O11 -> 146391.69 | D9: =C9-B9 -> 9947.3677 | E9: =IF(B9=0,0,D9/B9) -> 0.072904227 | F9: =IF(D9<=0,"Favorável","Desfavorável") -> Desfavorável | G9: =IF(D9<=0,"Despesa abaixo do orçamento: validar economia e possíveis postergações.","Despesa acima do orçamento: revisar causa, recorrência e plano de ação.") -> Despesa acima do orçamento: revisar causa, recorrência e plano de ação. | H9: =IF(ABS(E9)>=0.1,"Alta",IF(ABS(E9)>=0.05,"Média","Baixa")) -> Média

Sheet Dashboard_V2
A1: FP&A PERFORMANCE DASHBOARD | 2026
A2: Orçado x Realizado x Forecast | DRE gerencial, desvios, caixa e liquidez | N2: Mês | O2: Receita Orçada | P2: Receita Forecast | Q2: EBITDA Forecast | R2: Mês | S2: EBITDA Forecast
N3: Jan | O3: =Orcado_Forecast!D4+Orcado_Forecast!D5 -> 82500 | P3: =DRE_Gerencial!B6 -> 82000 | Q3: =DRE_Gerencial!B12 -> 14000 | R3: =N3 -> Jan | S3: =Q3 -> 14000
A4: Receita Forecast FY | C4: EBITDA Forecast FY | E4: Margem EBITDA | G4: Desvio EBITDA vs Orç. | I4: Saldo Final de Caixa | K4: Liquidez Dez/26 | N4: Fev | O4: =Orcado_Forecast!D10+Orcado_Forecast!D11 -> 83822.5 | P4: =DRE_Gerencial!C6 -> 79000 | Q4: =DRE_Gerencial!C12 -> 7000 | R4: =N4 -> Fev | S4: =Q4 -> 7000
A5: =DRE_Gerencial!O6 -> 1153513.7 | C5: =DRE_Gerencial!O12 -> 173758.99 | E5: =DRE_Gerencial!O13 -> 0.15063452 | G5: =DRE_Gerencial!P12 -> -2921.132 | I5: =Resumo_Mensal!G15 -> 223556.99 | K5: =Resumo_Mensal!J15 -> 6.2677272 | N5: Mar | O5: =Orcado_Forecast!D16+Orcado_Forecast!D17 -> 85167.99 | P5: =DRE_Gerencial!D6 -> 91000 | Q5: =DRE_Gerencial!D12 -> 16500 | R5: =N5 -> Mar | S5: =Q5 -> 16500
N6: Abr | O6: =Orcado_Forecast!D22+Orcado_Forecast!D23 -> 86536.89 | P6: =DRE_Gerencial!E6 -> 87000 | Q6: =DRE_Gerencial!E12 -> 11000 | R6: =N6 -> Abr | S6: =Q6 -> 11000
N7: Mai | O7: =Orcado_Forecast!D28+Orcado_Forecast!D29 -> 87929.6 | P7: =DRE_Gerencial!F6 -> 94000 | Q7: =DRE_Gerencial!F12 -> 15500 | R7: =N7 -> Mai | S7: =Q7 -> 15500
A8: LEITURA GERENCIAL | G8: STATUS DO FORECAST | N8: Jun | O8: =Orcado_Forecast!D34+Orcado_Forecast!D35 -> 89346.56 | P8: =DRE_Gerencial!G6 -> 97000 | Q8: =DRE_Gerencial!G12 -> 15000 | R8: =N8 -> Jun | S8: =Q8 -> 15000
A9: Meta Margem EBITDA | B9: =Premissas_V2!B11 -> 0.18 | G9: Realizado até | K9: Ago/2026 | N9: Jul | O9: =Orcado_Forecast!D40+Orcado_Forecast!D41 -> 90788.2 | P9: =DRE_Gerencial!H6 -> 101000 | Q9: =DRE_Gerencial!H12 -> 16500 | R9: =N9 -> Jul | S9: =Q9 -> 16500
A10: Margem EBITDA Forecast | B10: =DRE_Gerencial!O13 -> 0.15063452 | G10: Forecast | K10: Set–Dez/2026 | N10: Ago | O10: =Orcado_Forecast!D46+Orcado_Forecast!D47 -> 92254.95 | P10: =DRE_Gerencial!I6 -> 99000 | Q10: =DRE_Gerencial!I12 -> 13000 | R10: =N10 -> Ago | S10: =Q10 -> 13000
A11: Gap vs Meta | B11: =DRE_Gerencial!O13-Premissas_V2!B11 -> -0.029365476 | G11: Foco de atenção | K11: Margem EBITDA | N11: Set | O11: =Orcado_Forecast!D52+Orcado_Forecast!D53 -> 93747.26 | P11: =DRE_Gerencial!J6 -> 101673 | Q11: =DRE_Gerencial!J12 -> 14271.2 | R11: =N11 -> Set | S11: =Q11 -> 14271.2
A12: Liquidez Forecast | B12: =Resumo_Mensal!J15 -> 6.2677272 | N12: Out | O12: =Orcado_Forecast!D58+Orcado_Forecast!D59 -> 95265.59 | P12: =DRE_Gerencial!K6 -> 104423.22 | Q12: =DRE_Gerencial!K12 -> 15596.151 | R12: =N12 -> Out | S12: =Q12 -> 15596.151
N13: Nov | O13: =Orcado_Forecast!D64+Orcado_Forecast!D65 -> 96810.42 | P13: =DRE_Gerencial!L6 -> 107252.95 | Q13: =DRE_Gerencial!L12 -> 16976.736 | R13: =N13 -> Nov | S13: =Q13 -> 16976.736
N14: Dez | O14: =Orcado_Forecast!D70+Orcado_Forecast!D71 -> 98382.2 | P14: =DRE_Gerencial!M6 -> 110164.54 | Q14: =DRE_Gerencial!M12 -> 18414.901 | R14: =N14 -> Dez | S14: =Q14 -> 18414.901
N17: Categoria | O17: Desvio R$ | P17: Desvio %
N18: =Analise_Desvios!A4 -> Receita Operacional | O18: =Analise_Desvios!D4 -> 54756.148 | P18: =Analise_Desvios!E4 -> 0.05898174
N19: =Analise_Desvios!A5 -> Outras Receitas | O19: =Analise_Desvios!D5 -> 16205.394 | P19: =Analise_Desvios!E5 -> 0.10509708
N20: =Analise_Desvios!A6 -> Fornecedores | O20: =Analise_Desvios!D6 -> 16839.594 | P20: =Analise_Desvios!E6 -> 0.080471605
N21: =Analise_Desvios!A7 -> Pessoal | O21: =Analise_Desvios!D7 -> 34739.771 | P21: =Analise_Desvios!E7 -> 0.092326683
N22: =Analise_Desvios!A8 -> Tributos | O22: =Analise_Desvios!D8 -> 12355.941 | P22: =Analise_Desvios!E8 -> 0.067189726
N23: =Analise_Desvios!A9 -> Despesas Operacionais | O23: =Analise_Desvios!D9 -> 9947.3677 | P23: =Analise_Desvios!E9 -> 0.072904227
N26: Mês | O26: Saldo Acumulado | P26: Liquidez
N27: Jan | O27: =Resumo_Mensal!G4 -> 64000 | P27: =Resumo_Mensal!J4 -> 3.0294118
N28: Fev | O28: =Resumo_Mensal!G5 -> 71000 | P28: =Resumo_Mensal!J5 -> 3.0447531
N29: Mar | O29: =Resumo_Mensal!G6 -> 87500 | P29: =Resumo_Mensal!J6 -> 3.5600298
N30: Abr | O30: =Resumo_Mensal!G7 -> 98500 | P30: =Resumo_Mensal!J7 -> 3.7704678
N31: Mai | O31: =Resumo_Mensal!G8 -> 114000 | P31: =Resumo_Mensal!J8 -> 4.158528
N32: Jun | O32: =Resumo_Mensal!G9 -> 129000 | P32: =Resumo_Mensal!J9 -> 4.4159892
N33: Jul | O33: =Resumo_Mensal!G10 -> 145500 | P33: =Resumo_Mensal!J10 -> 4.7560815
N34: Ago | O34: =Resumo_Mensal!G11 -> 158500 | P34: =Resumo_Mensal!J11 -> 4.9909561
N35: Set | O35: =Resumo_Mensal!G12 -> 172750 | P35: =Resumo_Mensal!J12 -> 5.2804251
N36: Out | O36: =Resumo_Mensal!G13 -> 188304.7 | P36: =Resumo_Mensal!J13 -> 5.5898021
N37: Nov | O37: =Resumo_Mensal!G14 -> 205220.79 | P37: =Resumo_Mensal!J14 -> 5.9189476
N38: Dez | O38: =Resumo_Mensal!G15 -> 223556.99 | P38: =Resumo_Mensal!J15 -> 6.2677272

Sheet Centro_Custos
A1: ANÁLISE POR CENTRO DE CUSTO — FP&A
A3: Centro de Custo | B3: Orçado FY (R$) | C3: Forecast FY (R$) | D3: Desvio (R$) | E3: Desvio (%) | F3: Impacto | G3: Responsável | H3: Plano de ação
A4: Operações | B4: 310000 | C4: 326000 | D4: =C4-B4 -> 16000 | E4: =IFERROR(D4/B4,0) -> 0.051612903 | F4: =IF(D4<=0,"Favorável","Desfavorável") -> Desfavorável | G4: Gerência Operacional | H4: Renegociar fornecedores e revisar contratos.
A5: Comercial | B5: 148000 | C5: 156500 | D5: =C5-B5 -> 8500 | E5: =IFERROR(D5/B5,0) -> 0.057432432 | F5: =IF(D5<=0,"Favorável","Desfavorável") -> Desfavorável | G5: Gerência Comercial | H5: Revisar ROI de campanhas e comissões.
A6: Administrativo | B6: 205000 | C6: 214000 | D6: =C6-B6 -> 9000 | E6: =IFERROR(D6/B6,0) -> 0.043902439 | F6: =IF(D6<=0,"Favorável","Desfavorável") -> Desfavorável | G6: Controladoria | H6: Racionalizar despesas recorrentes.
A7: Tecnologia & Dados | B7: 112000 | C7: 126000 | D7: =C7-B7 -> 14000 | E7: =IFERROR(D7/B7,0) -> 0.125 | F7: =IF(D7<=0,"Favorável","Desfavorável") -> Desfavorável | G7: TI / Dados | H7: Priorizar projetos por retorno esperado.
A8: Pessoas & RH | B8: 221000 | C8: 229000 | D8: =C8-B8 -> 8000 | E8: =IFERROR(D8/B8,0) -> 0.036199095 | F8: =IF(D8<=0,"Favorável","Desfavorável") -> Desfavorável | G8: RH | H8: Acompanhar admissões e horas extras.
A9: Tributário | B9: 86400 | C9: 90200 | D9: =C9-B9 -> 3800 | E9: =IFERROR(D9/B9,0) -> 0.043981481 | F9: =IF(D9<=0,"Favorável","Desfavorável") -> Desfavorável | G9: Fiscal | H9: Revisar premissas tributárias do forecast.
A11: Total | B11: =SUM(B4:B9) -> 1082400 | C11: =SUM(C4:C9) -> 1141700 | D11: =C11-B11 -> 59300 | E11: =IFERROR(D11/B11,0) -> 0.054785661

Sheet Headcount
A1: HEADCOUNT & CUSTO DE PESSOAL — FP&A
A3: Área | B3: HC Inicial | C3: Admissões | D3: Desligamentos | E3: HC Final | F3: Salário Médio (R$) | G3: Custo Mensal (R$) | H3: Custo FY Orçado (R$) | I3: Custo FY Forecast (R$) | J3: Desvio (%)
A4: Finanças | B4: 5 | C4: 1 | D4: 0 | E4: =B4+C4-D4 -> 6 | F4: 6200 | G4: =E4*F4 -> 37200 | H4: 390000 | I4: 405000 | J4: =IFERROR(I4/H4-1,0) -> 0.038461538
A5: Operações | B5: 9 | C5: 2 | D5: 1 | E5: =B5+C5-D5 -> 10 | F5: 4300 | G5: =E5*F5 -> 43000 | H5: 475000 | I5: 492000 | J5: =IFERROR(I5/H5-1,0) -> 0.035789474
A6: Comercial | B6: 6 | C6: 1 | D6: 0 | E6: =B6+C6-D6 -> 7 | F6: 5100 | G6: =E6*F6 -> 35700 | H6: 382000 | I6: 395000 | J6: =IFERROR(I6/H6-1,0) -> 0.034031414
A7: Tecnologia & Dados | B7: 4 | C7: 2 | D7: 0 | E7: =B7+C7-D7 -> 6 | F7: 7800 | G7: =E7*F7 -> 46800 | H7: 410000 | I7: 445000 | J7: =IFERROR(I7/H7-1,0) -> 0.085365854
A8: Administrativo | B8: 5 | C8: 0 | D8: 1 | E8: =B8+C8-D8 -> 4 | F8: 4000 | G8: =E8*F8 -> 16000 | H8: 265000 | I8: 252000 | J8: =IFERROR(I8/H8-1,0) -> -0.049056604
A10: Total | B10: =SUM(B4:B8) -> 29 | C10: =SUM(C4:C8) -> 6 | D10: =SUM(D4:D8) -> 2 | E10: =SUM(E4:E8) -> 33 | G10: =SUM(G4:G8) -> 178700 | H10: =SUM(H4:H8) -> 1922000 | I10: =SUM(I4:I8) -> 1989000 | J10: =IFERROR(I10/H10-1,0) -> 0.034859521

Sheet Cenarios
A1: CENÁRIOS — BASE, OTIMISTA E CONSERVADOR
A3: Cenário | B3: Cresc. Receita | C3: Cresc. Custos | D3: Cresc. Pessoal | E3: Receita FY (R$) | F3: EBITDA FY (R$) | G3: Margem EBITDA | H3: Saldo Final (R$)
A4: Conservador | B4: -0.03 | C4: 0.05 | D4: 0.04 | E4: =DRE_Gerencial!O6*(1+B4) -> 1118908.3 | F4: =DRE_Gerencial!O12 + (DRE_Gerencial!O6*B4) - ABS(DRE_Gerencial!O7)*C4 - ABS(DRE_Gerencial!O9)*D4 -> 111408.14 | G4: =IFERROR(F4/E4,0) -> 0.099568603 | H4: =Resumo_Mensal!H15 + F4-DRE_Gerencial!O12 -> -23351.972
A5: Base | B5: 0 | C5: 0 | D5: 0 | E5: =DRE_Gerencial!O6*(1+B5) -> 1153513.7 | F5: =DRE_Gerencial!O12 + (DRE_Gerencial!O6*B5) - ABS(DRE_Gerencial!O7)*C5 - ABS(DRE_Gerencial!O9)*D5 -> 173758.99 | G5: =IFERROR(F5/E5,0) -> 0.15063452 | H5: =Resumo_Mensal!H15 + F5-DRE_Gerencial!O12 -> 38998.88
A6: Otimista | B6: 0.05 | C6: -0.02 | D6: -0.01 | E6: =DRE_Gerencial!O6*(1+B6) -> 1211189.4 | F6: =DRE_Gerencial!O12 + (DRE_Gerencial!O6*B6) - ABS(DRE_Gerencial!O7)*C6 - ABS(DRE_Gerencial!O9)*D6 -> 240066.79 | G6: =IFERROR(F6/E6,0) -> 0.19820747 | H6: =Resumo_Mensal!H15 + F6-DRE_Gerencial!O12 -> 105306.68
A8: Leitura | B8: Receita | C8: Custos | D8: Pessoal | E8: Receita FY | F8: EBITDA FY | G8: Margem | H8: Caixa
A9: Conservador | B9: Pressão de receita | C9: Inflação/fornecedores | D9: Maior custo de pessoal | E9: =E4 -> 1118908.3 | F9: =F4 -> 111408.14 | G9: =G4 -> 0.099568603 | H9: =H4 -> -23351.972
A10: Base | B10: Forecast atual | C10: Forecast atual | D10: Forecast atual | E10: =E5 -> 1153513.7 | F10: =F5 -> 173758.99 | G10: =G5 -> 0.15063452 | H10: =H5 -> 38998.88
A11: Otimista | B11: Upside comercial | C11: Eficiência de custos | D11: Produtividade | E11: =E6 -> 1211189.4 | F11: =F6 -> 240066.79 | G11: =G6 -> 0.19820747 | H11: =H6 -> 105306.68

Sheet Ponte_EBITDA
A1: PONTE DE VARIAÇÃO DO EBITDA — ORÇADO x FORECAST
A3: Driver | B3: Impacto no EBITDA (R$) | C3: Natureza | D3: Comentário
A4: EBITDA Orçado | B4: =DRE_Gerencial!N12 -> 176680.12 | C4: Base | D4: Ponto de partida do orçamento.
A5: Receita Operacional | B5: =DRE_Gerencial!P4 -> 54756.148 | C5: Favorável | D5: Crescimento de receita versus orçamento.
A6: Outras Receitas | B6: =DRE_Gerencial!P5 -> 16205.394 | C6: Favorável | D6: Outras receitas acima do plano.
A7: Fornecedores | B7: =-ABS(DRE_Gerencial!P7) -> -16839.594 | C7: Desfavorável | D7: Pressão de custos diretos.
A8: Pessoal | B8: =-ABS(DRE_Gerencial!P9) -> -34739.771 | C8: Desfavorável | D8: Custo de pessoal acima do orçamento.
A9: Tributos | B9: =-ABS(DRE_Gerencial!P10) -> -12355.941 | C9: Desfavorável | D9: Tributos acima do orçamento.
A10: Despesas Operacionais | B10: =-ABS(DRE_Gerencial!P11) -> -9947.3677 | C10: Desfavorável | D10: Opex acima do orçamento.
A11: EBITDA Forecast | B11: =DRE_Gerencial!O12 -> 173758.99 | C11: Final | D11: EBITDA após incorporação dos principais drivers.

Sheet Dashboard_V3
A1: DASHBOARD EXECUTIVO FP&A
A2: Budget • Actual • Forecast • Cenários • Centros de Custo • Headcount • Ponte EBITDA
A4: Receita Forecast FY | F4: EBITDA Forecast FY | K4: Margem EBITDA | P4: Liquidez Dez
A5: =DRE_Gerencial!O6 -> 1153513.7 | F5: =DRE_Gerencial!O12 -> 173758.99 | K5: =DRE_Gerencial!O13 -> 0.15063452 | P5: =Resumo_Mensal!J15 -> 6.2677272
A10: Cenário | B10: Receita FY | C10: EBITDA FY | D10: Margem EBITDA | E10: Saldo Final | F10: Cresc. Receita | G10: Cresc. Custos | H10: Cresc. Pessoal
A11: =Cenarios!A4 -> Conservador | B11: =Cenarios!E4 -> 1118908.3 | C11: =Cenarios!F4 -> 111408.14 | D11: =Cenarios!G4 -> 0.099568603 | E11: =Cenarios!H4 -> -23351.972 | F11: =Cenarios!B4 -> -0.03 | G11: =Cenarios!C4 -> 0.05 | H11: =Cenarios!D4 -> 0.04
A12: =Cenarios!A5 -> Base | B12: =Cenarios!E5 -> 1153513.7 | C12: =Cenarios!F5 -> 173758.99 | D12: =Cenarios!G5 -> 0.15063452 | E12: =Cenarios!H5 -> 38998.88 | F12: =Cenarios!B5 -> 0 | G12: =Cenarios!C5 -> 0 | H12: =Cenarios!D5 -> 0
A13: =Cenarios!A6 -> Otimista | B13: =Cenarios!E6 -> 1211189.4 | C13: =Cenarios!F6 -> 240066.79 | D13: =Cenarios!G6 -> 0.19820747 | E13: =Cenarios!H6 -> 105306.68 | F13: =Cenarios!B6 -> 0.05 | G13: =Cenarios!C6 -> -0.02 | H13: =Cenarios!D6 -> -0.01
A16: Centro de Custo | B16: Orçado | C16: Forecast | D16: Desvio | E16: Desvio % | F16: Impacto | J16: Área | K16: HC Inicial | L16: Admissões | M16: Deslig. | N16: HC Final | O16: Salário Médio | P16: Custo FY Orç. | Q16: Custo FY Fct. | R16: Desvio %
A17: =Centro_Custos!A4 -> Operações | B17: =Centro_Custos!B4 -> 310000 | C17: =Centro_Custos!C4 -> 326000 | D17: =Centro_Custos!D4 -> 16000 | E17: =Centro_Custos!E4 -> 0.051612903 | F17: =Centro_Custos!F4 -> Desfavorável | J17: =Headcount!A4 -> Finanças | K17: =Headcount!B4 -> 5 | L17: =Headcount!C4 -> 1 | M17: =Headcount!D4 -> 0 | N17: =Headcount!E4 -> 6 | O17: =Headcount!F4 -> 6200 | P17: =Headcount!H4 -> 390000 | Q17: =Headcount!I4 -> 405000 | R17: =Headcount!J4 -> 0.038461538
A18: =Centro_Custos!A5 -> Comercial | B18: =Centro_Custos!B5 -> 148000 | C18: =Centro_Custos!C5 -> 156500 | D18: =Centro_Custos!D5 -> 8500 | E18: =Centro_Custos!E5 -> 0.057432432 | F18: =Centro_Custos!F5 -> Desfavorável | J18: =Headcount!A5 -> Operações | K18: =Headcount!B5 -> 9 | L18: =Headcount!C5 -> 2 | M18: =Headcount!D5 -> 1 | N18: =Headcount!E5 -> 10 | O18: =Headcount!F5 -> 4300 | P18: =Headcount!H5 -> 475000 | Q18: =Headcount!I5 -> 492000 | R18: =Headcount!J5 -> 0.035789474
A19: =Centro_Custos!A6 -> Administrativo | B19: =Centro_Custos!B6 -> 205000 | C19: =Centro_Custos!C6 -> 214000 | D19: =Centro_Custos!D6 -> 9000 | E19: =Centro_Custos!E6 -> 0.043902439 | F19: =Centro_Custos!F6 -> Desfavorável | J19: =Headcount!A6 -> Comercial | K19: =Headcount!B6 -> 6 | L19: =Headcount!C6 -> 1 | M19: =Headcount!D6 -> 0 | N19: =Headcount!E6 -> 7 | O19: =Headcount!F6 -> 5100 | P19: =Headcount!H6 -> 382000 | Q19: =Headcount!I6 -> 395000 | R19: =Headcount!J6 -> 0.034031414
A20: =Centro_Custos!A7 -> Tecnologia & Dados | B20: =Centro_Custos!B7 -> 112000 | C20: =Centro_Custos!C7 -> 126000 | D20: =Centro_Custos!D7 -> 14000 | E20: =Centro_Custos!E7 -> 0.125 | F20: =Centro_Custos!F7 -> Desfavorável | J20: =Headcount!A7 -> Tecnologia & Dados | K20: =Headcount!B7 -> 4 | L20: =Headcount!C7 -> 2 | M20: =Headcount!D7 -> 0 | N20: =Headcount!E7 -> 6 | O20: =Headcount!F7 -> 7800 | P20: =Headcount!H7 -> 410000 | Q20: =Headcount!I7 -> 445000 | R20: =Headcount!J7 -> 0.085365854
A21: =Centro_Custos!A8 -> Pessoas & RH | B21: =Centro_Custos!B8 -> 221000 | C21: =Centro_Custos!C8 -> 229000 | D21: =Centro_Custos!D8 -> 8000 | E21: =Centro_Custos!E8 -> 0.036199095 | F21: =Centro_Custos!F8 -> Desfavorável | J21: =Headcount!A8 -> Administrativo | K21: =Headcount!B8 -> 5 | L21: =Headcount!C8 -> 0 | M21: =Headcount!D8 -> 1 | N21: =Headcount!E8 -> 4 | O21: =Headcount!F8 -> 4000 | P21: =Headcount!H8 -> 265000 | Q21: =Headcount!I8 -> 252000 | R21: =Headcount!J8 -> -0.049056604
A22: =Centro_Custos!A9 -> Tributário | B22: =Centro_Custos!B9 -> 86400 | C22: =Centro_Custos!C9 -> 90200 | D22: =Centro_Custos!D9 -> 3800 | E22: =Centro_Custos!E9 -> 0.043981481 | F22: =Centro_Custos!F9 -> Desfavorável
A26: Driver EBITDA | B26: Impacto (R$) | C26: Natureza | D26: Leitura | J26: INSIGHTS EXECUTIVOS
A27: =Ponte_EBITDA!A4 -> EBITDA Orçado | B27: =Ponte_EBITDA!B4 -> 176680.12 | C27: =Ponte_EBITDA!C4 -> Base | D27: =Ponte_EBITDA!D4 -> Ponto de partida do orçamento.
A28: =Ponte_EBITDA!A5 -> Receita Operacional | B28: =Ponte_EBITDA!B5 -> 54756.148 | C28: =Ponte_EBITDA!C5 -> Favorável | D28: =Ponte_EBITDA!D5 -> Crescimento de receita versus orçamento. | J28: 1. Receita forecast supera o orçamento, mas o ganho é parcialmente absorvido por custos e pessoal.
A29: =Ponte_EBITDA!A6 -> Outras Receitas | B29: =Ponte_EBITDA!B6 -> 16205.394 | C29: =Ponte_EBITDA!C6 -> Favorável | D29: =Ponte_EBITDA!D6 -> Outras receitas acima do plano. | J29: 2. Cenários permitem medir sensibilidade do EBITDA a receita, custos e headcount.
A30: =Ponte_EBITDA!A7 -> Fornecedores | B30: =Ponte_EBITDA!B7 -> -16839.594 | C30: =Ponte_EBITDA!C7 -> Desfavorável | D30: =Ponte_EBITDA!D7 -> Pressão de custos diretos. | J30: 3. Centros de custo com desvio desfavorável devem ter plano de ação e responsável.
A31: =Ponte_EBITDA!A8 -> Pessoal | B31: =Ponte_EBITDA!B8 -> -34739.771 | C31: =Ponte_EBITDA!C8 -> Desfavorável | D31: =Ponte_EBITDA!D8 -> Custo de pessoal acima do orçamento. | J31: 4. Headcount conecta decisões de contratação ao impacto financeiro anual.
A32: =Ponte_EBITDA!A9 -> Tributos | B32: =Ponte_EBITDA!B9 -> -12355.941 | C32: =Ponte_EBITDA!C9 -> Desfavorável | D32: =Ponte_EBITDA!D9 -> Tributos acima do orçamento. | J32: 5. A ponte de EBITDA explica os principais drivers entre orçamento e forecast.
A33: =Ponte_EBITDA!A10 -> Despesas Operacionais | B33: =Ponte_EBITDA!B10 -> -9947.3677 | C33: =Ponte_EBITDA!C10 -> Desfavorável | D33: =Ponte_EBITDA!D10 -> Opex acima do orçamento.
A34: =Ponte_EBITDA!A11 -> EBITDA Forecast | B34: =Ponte_EBITDA!B11 -> 173758.99 | C34: =Ponte_EBITDA!C11 -> Final | D34: =Ponte_EBITDA!D11 -> EBITDA após incorporação dos principais drivers.
